scmusketeers/__init__.py
scmusketeers/__main__.py
scmusketeers/arguments/__init__.py
scmusketeers/arguments/ae_param.py
scmusketeers/arguments/class_param.py
scmusketeers/arguments/dann_param.py
scmusketeers/arguments/neptune_log.py
scmusketeers/arguments/runfile.py
scmusketeers/run_musk.py
scmusketeers/tools/VERSION
scmusketeers/tools/__init__.py
scmusketeers/tools/clust_compute.py
scmusketeers/tools/layers.py
scmusketeers/tools/loss.py
scmusketeers/tools/models.py
scmusketeers/tools/permutation.py
scmusketeers/tools/plot.py
scmusketeers/tools/utils.py
scmusketeers/transfer/__init__.py
scmusketeers/transfer/dataset_tf.py
scmusketeers/transfer/experiment.py
scmusketeers/transfer/freeze.py
scmusketeers/transfer/optimize_model.py
scmusketeers/workflow/__init__.py
scmusketeers/workflow/benchmark.py
scmusketeers/workflow/benchmark_models.py
scmusketeers/workflow/dataset.py
scmusketeers/workflow/hyperparameters.py
scmusketeers/workflow/run_workflow.py
sc_musketeers-0.4.2.dist-info/LICENSE
sc_musketeers-0.4.2.dist-info/METADATA
sc_musketeers-0.4.2.dist-info/WHEEL
sc_musketeers-0.4.2.dist-info/entry_points.txt
sc_musketeers-0.4.2.dist-info/RECORD
