Metadata-Version: 2.1
Name: sc-musketeers
Version: 0.4.2
Summary: A tri-partite modular autoencoder for addressing imbalanced cell type annotation and batch effect reduction
Home-page: https://sc-musketeers.readthedocs.io/
License: MIT
Author: AntoineCollin
Requires-Python: >=3.10,<4.0
Classifier: License :: OSI Approved :: MIT License
Classifier: Programming Language :: Python :: 3
Classifier: Programming Language :: Python :: 3.10
Classifier: Programming Language :: Python :: 3.11
Classifier: Programming Language :: Python :: 3.12
Requires-Dist: keras (>=3.3.3,<4.0.0)
Requires-Dist: matplotlib (>=3.9.3,<4.0.0)
Requires-Dist: neptune (>=1.10.4,<2.0.0)
Requires-Dist: numpy (>=1.23,<2.0)
Requires-Dist: pandas (>=2.2.3,<3.0.0)
Requires-Dist: pillow (>=11.0.0,<12.0.0)
Requires-Dist: poetry (>=1.8.1,<2.0.0)
Requires-Dist: pympler (>=1.0.1,<2.0.0)
Requires-Dist: scanpy (>=1.10.1,<2.0.0)
Requires-Dist: scikit-learn (>=1.5.2,<2.0.0)
Requires-Dist: seaborn (>=0.13.2,<0.14.0)
Requires-Dist: tensorflow (>=2.10.0,<3.0.0)
Project-URL: Repository, https://github.com/AntoineCollin/scMusketeers/
